recarguide/__init__.py
recarguide/__main__.py
recarguide-0.0.1.dist-info/DESCRIPTION.rst
recarguide-0.0.1.dist-info/METADATA
recarguide-0.0.1.dist-info/RECORD
recarguide-0.0.1.dist-info/WHEEL
recarguide-0.0.1.dist-info/metadata.json
recarguide-0.0.1.dist-info/top_level.txt
